{
  "generator-jhipster": {
    "promptValues": {
      "packageName": "com.mycompany.myapp"
    },
    "jhipsterVersion": "5.3.4",
    "applicationType": "monolith",
    "baseName": "myappdemo06",
    "packageName": "com.mycompany.myapp",
    "packageFolder": "com/mycompany/myapp",
    "serverPort": "8080",
    "authenticationType": "session",
    "cacheProvider": "ehcache",
    "enableHibernateCache": true,
    "websocket": "spring-websocket",
    "databaseType": "sql",
    "devDatabaseType": "mysql",
    "prodDatabaseType": "mysql",
    "searchEngine": "elasticsearch",
    "messageBroker": false,
    "serviceDiscoveryType": false,
    "buildTool": "gradle",
    "enableSwaggerCodegen": false,
    "rememberMeKey": "59658ea11d62a4e92a800334dde1a5adfa743664aa8fa55651b0519328aec8053c08f62c0c5e6e1f7557b933116bf4f4ea67",
    "clientFramework": "react",
    "useSass": true,
    "clientPackageManager": "npm",
    "testFrameworks": [],
    "jhiPrefix": "jhi",
    "enableTranslation": false
  }
}